dunderlab/api/__init__.py
dunderlab/api/aioapi.py
dunderlab/api/utils.py
dunderlab/api/.ipynb_checkpoints/__init__-checkpoint.py
dunderlab/api/.ipynb_checkpoints/utils-checkpoint.py
dunderlab/django/timescaledbapp/__init__.py
dunderlab/django/timescaledbapp/admin.py
dunderlab/django/timescaledbapp/apps.py
dunderlab/django/timescaledbapp/db_router.py
dunderlab/django/timescaledbapp/filters.py
dunderlab/django/timescaledbapp/models.py
dunderlab/django/timescaledbapp/paginators.py
dunderlab/django/timescaledbapp/permissions.py
dunderlab/django/timescaledbapp/serializers.py
dunderlab/django/timescaledbapp/urls.py
dunderlab/django/timescaledbapp/views.py
dunderlab/django/timescaledbapp/management/__init__.py
dunderlab/django/timescaledbapp/management/commands/__init___.py
dunderlab/django/timescaledbapp/management/commands/create_groups.py
dunderlab/django/timescaledbapp/migrations/0001_initial.py
dunderlab/django/timescaledbapp/migrations/0002_timescaledb.py
dunderlab/django/timescaledbapp/migrations/__init__.py
dunderlab_timescaledbapp-0.1.17.data/scripts/timescaledbapp_create
dunderlab_timescaledbapp-0.1.17.dist-info/LICENSE.md
dunderlab_timescaledbapp-0.1.17.dist-info/METADATA
dunderlab_timescaledbapp-0.1.17.dist-info/WHEEL
dunderlab_timescaledbapp-0.1.17.dist-info/top_level.txt
dunderlab_timescaledbapp-0.1.17.dist-info/RECORD
