Metadata-Version: 2.1
Name: dunderlab-timescaledbapp
Version: 0.1.17
Summary: Django TimeScale DB App
Download-URL: https://github.com/dunderlab/python-django.timescaledbapp
Author: Yeison Cardona
Author-email: yencardonaal@unal.edu.co
Maintainer: Yeison Cardona
Maintainer-email: yencardonaal@unal.edu.co
License: BSD-2-Clause
Classifier: Development Status :: 4 - Beta
Classifier: License :: OSI Approved :: BSD License
Classifier: Programming Language :: Python :: 3.11
Classifier: Programming Language :: Python :: 3.10
Requires-Python: >=3.10
License-File: LICENSE.md
Requires-Dist: psycopg2-binary
Requires-Dist: aiohttp
Requires-Dist: numpy
